multiped/Engine.py
multiped/Gait.py
multiped/Robot.py
multiped/Servo.py
multiped/__init__.py
multiped/bin/__init__.py
multiped/bin/get_leg_angles.py
multiped/bin/get_leg_info.py
multiped/jsonFile.py
multiped/kinematics3.py
multiped/kinematics4.py
multiped-0.5.1.dist-info/LICENSE
multiped-0.5.1.dist-info/WHEEL
multiped-0.5.1.dist-info/METADATA
multiped-0.5.1.dist-info/RECORD
