Metadata-Version: 2.1
Name: multiped
Version: 0.5.1
Summary: Yet another robot python driver
Home-page: https://pypi.org/project/multiped/
License: MIT
Keywords: dynamixel,servo,smart,multiped,hexapod,quadruped
Author: walchko
Author-email: walchko@users.noreply.github.com
Requires-Python: >=3.6
Classifier: Development Status :: 4 - Beta
Classifier: Intended Audience :: Developers
Classifier: License :: OSI Approved :: MIT License
Classifier: Operating System :: OS Independent
Classifier: Programming Language :: Python :: 3
Classifier: Programming Language :: Python :: 3.6
Classifier: Programming Language :: Python :: 3.7
Classifier: Programming Language :: Python :: 3.8
Classifier: Topic :: Software Development :: Libraries
Classifier: Topic :: Software Development :: Libraries :: Application Frameworks
Classifier: Topic :: Software Development :: Libraries :: Python Modules
Requires-Dist: colorama
Requires-Dist: mdh
Requires-Dist: pyservos (>=2.0.1)
Requires-Dist: simplejson
Project-URL: Repository, http://github.com/MultipedRobotics/multiped
